mysqlmigratorpostgree/__init__.py
mysqlmigratorpostgree/connect_mysql.py
mysqlmigratorpostgree/connect_postgresql.py
mysqlmigratorpostgree/migrator.py
mysqlmigratorpostgree-0.2.0.dist-info/LICENCE
mysqlmigratorpostgree-0.2.0.dist-info/METADATA
mysqlmigratorpostgree-0.2.0.dist-info/WHEEL
mysqlmigratorpostgree-0.2.0.dist-info/top_level.txt
mysqlmigratorpostgree-0.2.0.dist-info/RECORD
