Metadata-Version: 2.1
Name: mysqlmigratorpostgree
Version: 0.2.0
Summary: Libreria pensada para migrar datos a postgresql de manera versatil auto modulando simplificado el codigo
Home-page: https://github.com/archenthusiastic/mysql-migrator-postgreesql
Author: archenthusiastic
Author-email: abuawadsantiago@gmail.com
License: MIT
Classifier: Programming Language :: Python :: 3
Classifier: License :: OSI Approved :: MIT License
Classifier: Operating System :: OS Independent
Requires-Python: >=3.7
License-File: LICENCE
Requires-Dist: mysql-connector-python
Requires-Dist: psycopg2
